petal_plaid_python-1.0.0.dist-info/METADATA
petal_plaid_python-1.0.0.dist-info/RECORD
petal_plaid_python-1.0.0.dist-info/WHEEL
petal_plaid_python-1.0.0.dist-info/top_level.txt
plaid/__init__.py
plaid/client.py
plaid/errors.py
plaid/requester.py
plaid/utils.py
plaid/version.py
plaid/api/__init__.py
plaid/api/accounts.py
plaid/api/api.py
plaid/api/assets.py
plaid/api/auth.py
plaid/api/categories.py
plaid/api/credit_details.py
plaid/api/identity.py
plaid/api/income.py
plaid/api/institutions.py
plaid/api/item.py
plaid/api/processor.py
plaid/api/sandbox.py
plaid/api/transactions.py
tests/__init__.py
tests/integration/__init__.py
tests/integration/test_accounts.py
tests/integration/test_assets.py
tests/integration/test_auth.py
tests/integration/test_categories.py
tests/integration/test_credit_details.py
tests/integration/test_identity.py
tests/integration/test_income.py
tests/integration/test_institutions.py
tests/integration/test_item.py
tests/integration/test_processor.py
tests/integration/test_transactions.py
tests/integration/util.py
tests/unit/__init__.py
tests/unit/test_errors.py
