Metadata-Version: 2.1
Name: petal-plaid-python
Version: 1.0.0
Summary: Python client library for the Plaid API and Link v2.3.3
Home-page: https://github.com/plaid/plaid-python
Author: Plaid Technologies
Author-email: developers@plaid.com
License: MIT
Download-URL: https://github.com/plaid/plaid-python/tarball/v1.0.0
Keywords: api,client,plaid
Platform: UNKNOWN
Classifier: Programming Language :: Python
Classifier: Programming Language :: Python :: 2
Classifier: Programming Language :: Python :: 2.7
Classifier: Programming Language :: Python :: 3
Classifier: Programming Language :: Python :: 3.4
Classifier: Programming Language :: Python :: 3.5
Classifier: Programming Language :: Python :: 3.6
Classifier: Topic :: Software Development :: Libraries :: Python Modules
Classifier: Environment :: Web Environment
Requires-Dist: requests (>=2.7.0)
